pae/sqlalchemy/__init__.py
pae/sqlalchemy/checks.py
pae/sqlalchemy/default_settings.py
pae/sqlalchemy/factory.py
pyapp_ext/sqlalchemy/__init__.py
pyapp_ext/sqlalchemy/checks.py
pyapp_ext/sqlalchemy/default_settings.py
pyapp_ext/sqlalchemy/factory.py
pyApp_SQLAlchemy-1.0.1.dist-info/LICENSE
pyApp_SQLAlchemy-1.0.1.dist-info/METADATA
pyApp_SQLAlchemy-1.0.1.dist-info/WHEEL
pyApp_SQLAlchemy-1.0.1.dist-info/entry_points.txt
pyApp_SQLAlchemy-1.0.1.dist-info/top_level.txt
pyApp_SQLAlchemy-1.0.1.dist-info/RECORD
