Metadata-Version: 2.1
Name: pyApp-SQLAlchemy
Version: 1.0.1
Summary: SQLAlchemy Extension for PyApp
Home-page: https://github.com/pyapp-org/pyapp.sqlalchemy
Author: Tim Savage
Author-email: tim@savage.company
License: BSD-3-Clause
Keywords: application,framework
Platform: any
Classifier: Development Status :: 5 - Production/Stable
Classifier: Intended Audience :: Developers
Classifier: License :: OSI Approved :: BSD License
Classifier: Operating System :: OS Independent
Classifier: Topic :: Software Development :: Libraries :: Python Modules
Classifier: Topic :: Software Development :: Libraries :: Application Frameworks
Classifier: Programming Language :: Python :: 3
Classifier: Programming Language :: Python :: 3.6
Classifier: Programming Language :: Python :: 3.7
Classifier: Programming Language :: Python :: Implementation :: CPython
Classifier: Programming Language :: Python :: Implementation :: PyPy
Requires-Python: >=3.6
Requires-Dist: pyapp (>=4.0)
Requires-Dist: sqlalchemy
Provides-Extra: dev
Requires-Dist: docutils ; extra == 'dev'
Requires-Dist: black ; extra == 'dev'
